AUTHORS
CHANGELOG.txt
DESCRIPTION
LICENSE
MANIFEST.in
README.rst
setup.cfg
setup.py
django_dynamic_content.egg-info/PKG-INFO
django_dynamic_content.egg-info/SOURCES.txt
django_dynamic_content.egg-info/dependency_links.txt
django_dynamic_content.egg-info/requires.txt
django_dynamic_content.egg-info/top_level.txt
dynamic_content/__init__.py
dynamic_content/admin.py
dynamic_content/models.py
dynamic_content/urls.py
dynamic_content/views.py
dynamic_content/migrations/0001_initial.py
dynamic_content/migrations/0002_auto_20141128_0209.py
dynamic_content/migrations/0003_auto_20150701_0755.py
dynamic_content/migrations/0004_auto_20170805_0152.py
dynamic_content/migrations/0005_auto_20170805_0157.py
dynamic_content/migrations/__init__.py
dynamic_content/south_migrations/0001_initial.py
dynamic_content/south_migrations/0002_auto__chg_field_dynamiccontenttranslation_content__add_unique_dynamicc.py
dynamic_content/south_migrations/0003_auto__add_field_dynamiccontenttranslation_content_html__chg_field_dyna.py
dynamic_content/south_migrations/__init__.py
dynamic_content/templatetags/__init__.py
dynamic_content/templatetags/dynamic_content_tags.py
dynamic_content/tests/__init__.py
dynamic_content/tests/dynamic_content_tags_tests.py
dynamic_content/tests/models_tests.py
dynamic_content/tests/settings.py
dynamic_content/tests/test_settings.py
dynamic_content/tests/urls.py
dynamic_content/tests/test_app/__init__.py
dynamic_content/tests/test_app/models.py
dynamic_content/tests/test_app/templates/400.html
dynamic_content/tests/test_app/templates/500.html