Metadata-Version: 1.0
Name: django-dynamic-content
Version: 0.3.2
Summary: A reusable Django app that allows to place dynamic content into templates.
